castellum_pseudonyms.py
castellum_pseudonyms-0.0.3.dist-info/LICENSE
castellum_pseudonyms-0.0.3.dist-info/METADATA
castellum_pseudonyms-0.0.3.dist-info/WHEEL
castellum_pseudonyms-0.0.3.dist-info/top_level.txt
castellum_pseudonyms-0.0.3.dist-info/RECORD
